pydat/__init__.py
pydat/pydat_module.py
pyndat/__init__.py
pyndat/pyndat_module.py
pyndat-0.0.2.dist-info/LICENSE
pyndat-0.0.2.dist-info/METADATA
pyndat-0.0.2.dist-info/WHEEL
pyndat-0.0.2.dist-info/top_level.txt
pyndat-0.0.2.dist-info/RECORD
