Metadata-Version: 2.1
Name: pyndat
Version: 0.0.2
Summary: A toolbox for analyzing hydrological drought
Home-page: https://github.com/savalann/pydat
Author: Savalan Naser Neisary
Author-email: savalan.neisary@gmail.com
License: Apache License 2.0
Keywords: Drought Analysis,Hydrology
Classifier: Intended Audience :: Education
Classifier: Programming Language :: Python :: 3
Classifier: Operating System :: MacOS :: MacOS X
Classifier: Operating System :: Microsoft :: Windows
Classifier: Operating System :: POSIX :: Linux
Requires-Python: >=3.9
License-File: LICENSE
Requires-Dist: numpy (>=1.26.4)
Requires-Dist: pandas (>=2.2.1)
Requires-Dist: matplotlib (>=3.8.0)
Requires-Dist: dataretrieval (>=1.0.6)
